{
  "games": [
    {
      "id": "gacha_city_lockpick_circular",
      "version": "1.0.0",
      "dllFileName": "CocoKey.Games.GachaCity.LockpickCircular.dll",
      "sha256": "4445241bd3c96aed676ca500e1e39c20d1e8c67b8f9978b5b72ab87ffbbc2d21",
      "downloadUrl": "https://github.com/zx-devstudio/cocokey-releases/releases/download/game-gacha_city_lockpick_circular-v1.0.0/CocoKey.Games.GachaCity.LockpickCircular.dll",
      "displayName": "Lockpick: Xoay màu",
      "description": "Thử thách kỹ năng mở khóa! Xoay vòng tròn để tìm điểm sweet spot và mở khóa thành công.",
      "author": "ZX-DEV",
      "price": 50000,
      "serverId": "gachacity",
      "iconBase64": "",
      "backgroundImageBase64": ""
    },
    {
      "id": "gacha_city_lockpick_untangle",
      "version": "1.0.0",
      "dllFileName": "CocoKey.Games.GachaCity.LockpickUntangle.dll",
      "sha256": "2dd81ca20254eb351ef62cfcc6bfd2bc803dcb93015a60e95d2a673e74dd4d10",
      "downloadUrl": "https://github.com/zx-devstudio/cocokey-releases/releases/download/game-gacha_city_lockpick_untangle-v1.0.0/CocoKey.Games.GachaCity.LockpickUntangle.dll",
      "displayName": "Lockpick: Gỡ rối",
      "description": "Thử thách kỹ năng mở khóa! Gỡ rối các vòng để mở khóa thành công.",
      "author": "ZX-DEV",
      "price": 50000,
      "serverId": "gachacity",
      "iconBase64": "",
      "backgroundImageBase64": ""
    },
    {
      "id": "gacha_city_harvest_weed",
      "version": "1.0.0",
      "dllFileName": "CocoKey.Games.GachaCity.HarvestWeed.dll",
      "sha256": "ababa0afee6e76da0fda78de026a3a26749e7be9992bdbdf299846f89aac085b",
      "downloadUrl": "https://github.com/zx-devstudio/cocokey-releases/releases/download/game-gacha_city_harvest_weed-v1.0.0/CocoKey.Games.GachaCity.HarvestWeed.dll",
      "displayName": "Hái bông",
      "description": "Tiện ích tự động hái bông. Hỗ trợ cả mod đồ họa.",
      "author": "ZX-DEV",
      "price": 50000,
      "serverId": "gachacity",
      "iconBase64": "",
      "backgroundImageBase64": ""
    },
    {
      "id": "gacha_city_fishing_audition",
      "version": "1.0.0",
      "dllFileName": "CocoKey.Games.GachaCity.FishingAudition.dll",
      "sha256": "34cd1e8e6f27932dabdbc0b552b5c2af55a698d8bf4d8b377ddd6786b69d0bc6",
      "downloadUrl": "https://github.com/zx-devstudio/cocokey-releases/releases/download/game-gacha_city_fishing_audition-v1.0.0/CocoKey.Games.GachaCity.FishingAudition.dll",
      "displayName": "Câu cá: Audition (Lv1-3)",
      "description": "",
      "author": "ZX-DEV",
      "price": 150000,
      "serverId": "gachacity",
      "iconBase64": "",
      "backgroundImageBase64": ""
    },
    {
      "id": "gacha_city_fishing_audition_2",
      "version": "1.0.0",
      "dllFileName": "CocoKey.Games.GachaCity.FishingAudition2.dll",
      "sha256": "80dced7382287a557d3215473ffaaeb2b8d9c41e76d8b6dae40f59d4c227ba7b",
      "downloadUrl": "https://github.com/zx-devstudio/cocokey-releases/releases/download/game-gacha_city_fishing_audition_2-v1.0.0/CocoKey.Games.GachaCity.FishingAudition2.dll",
      "displayName": "Câu cá: Audition (Lv4-5)",
      "description": "",
      "author": "ZX-DEV",
      "price": 150000,
      "serverId": "gachacity",
      "iconBase64": "",
      "backgroundImageBase64": ""
    },
    {
      "id": "luquy_fishing_audition",
      "version": "1.0.0",
      "dllFileName": "CocoKey.Games.LuQuy.FishingAudition.dll",
      "sha256": "4fff88931b896c1d5c022d7afc09fb59b8e13ac2638e09f572c0f671b6e66efb",
      "downloadUrl": "https://github.com/zx-devstudio/cocokey-releases/releases/download/game-luquy_fishing_audition-v1.0.0/CocoKey.Games.LuQuy.FishingAudition.dll",
      "displayName": "Câu cá: Audition",
      "description": "",
      "author": "ZX-DEV",
      "price": 100000,
      "serverId": "luquy",
      "iconBase64": "",
      "backgroundImageBase64": ""
    },
    {
      "id": "gacha_city_auto_drive",
      "version": "1.0.0",
      "dllFileName": "CocoKey.Games.GachaCity.AutoDrive.dll",
      "sha256": "748bde066f0e26afab09fbf5314062e24564c3bb930c917b5c20d291524c131e",
      "downloadUrl": "https://github.com/zx-devstudio/cocokey-releases/releases/download/game-gacha_city_auto_drive-v1.0.0/CocoKey.Games.GachaCity.AutoDrive.dll",
      "displayName": "Tự lái",
      "description": "",
      "author": "ZX-DEV",
      "price": 10000,
      "serverId": "gachacity",
      "iconBase64": "",
      "backgroundImageBase64": ""
    },
    {
      "id": "gacha_city_consumables",
      "version": "1.0.0",
      "dllFileName": "CocoKey.Games.GachaCity.Consumables.dll",
      "sha256": "efe694cab7bc82d0b6ad738297772a890875859762f4682debe3294cf1fc8eb3",
      "downloadUrl": "https://github.com/zx-devstudio/cocokey-releases/releases/download/game-gacha_city_consumables-v1.0.0/CocoKey.Games.GachaCity.Consumables.dll",
      "displayName": "Ăn uống",
      "description": "",
      "author": "ZX-DEV",
      "price": 15000,
      "serverId": "gachacity",
      "iconBase64": "",
      "backgroundImageBase64": ""
    },
    {
      "id": "gacha_city_orange_grape",
      "version": "1.0.0",
      "dllFileName": "CocoKey.Games.GachaCity.OrangeGrape.dll",
      "sha256": "86fa502fa33ce56291fc2e76e7450d9c208b198795e2193921cf84c64ff7f790",
      "downloadUrl": "https://github.com/zx-devstudio/cocokey-releases/releases/download/game-gacha_city_orange_grape-v1.0.0/CocoKey.Games.GachaCity.OrangeGrape.dll",
      "displayName": "Hái Cam Nho",
      "description": "",
      "author": "ZX-DEV",
      "price": 30000,
      "serverId": "gachacity",
      "iconBase64": "",
      "backgroundImageBase64": ""
    },
    {
      "id": "gacha_city_cut_rock",
      "version": "1.0.0",
      "dllFileName": "CocoKey.Games.GachaCity.CutRock.dll",
      "sha256": "bbf7cb6539f0291f454d6d02c48d606a0e7942e8d1305d9b15da190cf5ba5824",
      "downloadUrl": "https://github.com/zx-devstudio/cocokey-releases/releases/download/game-gacha_city_cut_rock-v1.0.0/CocoKey.Games.GachaCity.CutRock.dll",
      "displayName": "Cắt Đá",
      "description": "",
      "author": "ZX-DEV",
      "price": 30000,
      "serverId": "gachacity",
      "iconBase64": "",
      "backgroundImageBase64": ""
    },
    {
      "id": "gacha_city_dry_weed",
      "version": "1.0.0",
      "dllFileName": "CocoKey.Games.GachaCity.DryWeed.dll",
      "sha256": "0b7aee411c93604be65afcf2159f8c3800a37a67f935977d303cd983b7bcc288",
      "downloadUrl": "https://github.com/zx-devstudio/cocokey-releases/releases/download/game-gacha_city_dry_weed-v1.0.0/CocoKey.Games.GachaCity.DryWeed.dll",
      "displayName": "Sấy cỏ",
      "description": "",
      "author": "ZX-DEV",
      "price": 30000,
      "serverId": "gachacity",
      "iconBase64": "",
      "backgroundImageBase64": ""
    },
    {
      "id": "gacha_city_fishing_character_2",
      "version": "1.0.0",
      "dllFileName": "CocoKey.Games.GachaCity.FishingCharacter2.dll",
      "sha256": "8a4c145f304270c150a321f307778b6da64f00a404283c1eace89bb524f6647e",
      "downloadUrl": "https://github.com/zx-devstudio/cocokey-releases/releases/download/game-gacha_city_fishing_character_2-v1.0.0/CocoKey.Games.GachaCity.FishingCharacter2.dll",
      "displayName": "Câu cá: rương",
      "description": "Tính năng đang trong quá trình phát triển. Vui lòng đợi!!!",
      "author": "ZX-DEV",
      "price": 100000,
      "serverId": "gachacity",
      "iconBase64": "",
      "backgroundImageBase64": ""
    },
    {
      "id": "luquy_data_repair",
      "version": "1.0.0",
      "dllFileName": "CocoKey.Games.LuQuy.DataRepair.dll",
      "sha256": "5c618b8a1fabc336ed065c8c5425f72bba11dcbd7797c775fd7b25bda62f2f4e",
      "downloadUrl": "https://github.com/zx-devstudio/cocokey-releases/releases/download/game-luquy_data_repair-v1.0.0/CocoKey.Games.LuQuy.DataRepair.dll",
      "displayName": "Data Repair",
      "description": "Tính năng đang trong quá trình phát triển. Vui lòng đợi!!!",
      "author": "ZX-DEV",
      "price": 50000,
      "serverId": "luquy",
      "iconBase64": "",
      "backgroundImageBase64": ""
    }
  ]
}