{
  "games": [
    {
      "id": "gacha_city_lockpick_circular",
      "version": "1.0.0",
      "dllFileName": "CocoKey.Games.GachaCity.LockpickCircular.dll",
      "sha256": "97a3a2b12c39314723a8499edae8356c0d787443814f1a74cde8bc71375a6716",
      "downloadUrl": "https://github.com/zx-devstudio/cocokey-releases/releases/download/game-gacha_city_lockpick_circular-v1.0.0/CocoKey.Games.GachaCity.LockpickCircular.dll",
      "displayName": "Lockpick 1",
      "description": "Thử thách kỹ năng mở khóa! Xoay vòng tròn để tìm điểm sweet spot và mở khóa thành công.",
      "author": "ZX-DEV",
      "price": 50000,
      "genre": {
        "name": "GachaCity",
        "icon": "",
        "description": "FiveM Server"
      },
      "iconBase64": "",
      "backgroundImageBase64": ""
    }
  ]
}